voltron_web/__init__.py
voltron_web/ui.py
voltron_web/static/build/bundle.js
voltron_web/templates/index.html
voltron_web-0.1.1.dist-info/DESCRIPTION.rst
voltron_web-0.1.1.dist-info/METADATA
voltron_web-0.1.1.dist-info/RECORD
voltron_web-0.1.1.dist-info/WHEEL
voltron_web-0.1.1.dist-info/metadata.json
voltron_web-0.1.1.dist-info/top_level.txt
