Metadata-Version: 2.0
Name: voltron-web
Version: 0.1.1
Summary: Voltron web interface
Home-page: https://github.com/snare/voltron-web
Author: snare
Author-email: snare@ho.ax
License: MIT
Keywords: voltron voltron-web debugger ui gdb lldb vdb
Platform: UNKNOWN
Requires-Dist: flask
Requires-Dist: flask-restful
